uinex/__init__.py
uinex/__main__.py
uinex/core/__init__.py
uinex/core/geometry.py
uinex/core/widget.py
uinex/version.py
uinex/widgets/__init__.py
uinex/widgets/button.py
uinex/widgets/checkbutton.py
uinex/widgets/combobox.py
uinex/widgets/entry.py
uinex/widgets/floodgauge.py
uinex/widgets/frame.py
uinex/widgets/label.py
uinex/widgets/listbox.py
uinex/widgets/menubutton.py
uinex/widgets/meter.py
uinex/widgets/progressbar.py
uinex/widgets/radiobutton.py
uinex/widgets/scale.py
uinex/widgets/separator.py
uinex/widgets/sizegrip.py
uinex/widgets/spinbox.py
uinex/widgets/textbox.py
uinex/widgets/treeview.py
uinex-0.1.0.dist-info/WHEEL
uinex-0.1.0.dist-info/entry_points.txt
uinex-0.1.0.dist-info/METADATA
uinex-0.1.0.dist-info/RECORD
