Metadata-Version: 2.4
Name: uinex
Version: 0.1.0
Summary: Create modern looking GUIs with pygame.
Keywords: pygame,uinex,game ui,2d,games,development,gui,library
Author: Sackey Ezekiel Etrue, PygameUI Contributers
Author-email: Sackey Ezekiel Etrue <sackeyetrue@gmail.com>
License-Expression: MIT
Classifier: Intended Audience :: Developers
Classifier: License :: OSI Approved :: MIT License
Classifier: Programming Language :: Python :: 3
Classifier: Programming Language :: Python :: 3.9
Classifier: Programming Language :: Python :: 3.10
Classifier: Programming Language :: Python :: 3.11
Classifier: Programming Language :: Python :: 3.12
Classifier: Topic :: Games/Entertainment
Classifier: Topic :: Multimedia :: Graphics
Classifier: Topic :: Software Development :: Libraries :: Application Frameworks
Classifier: Operating System :: Microsoft :: Windows
Requires-Dist: pillow>=11.3.0
Requires-Dist: pygame
Requires-Dist: pytest ; extra == 'dev'
Maintainer: Sackey Ezekiel Etrue
Maintainer-email: Sackey Ezekiel Etrue <sackeyetrue@gmail.com>
Requires-Python: >=3.13
Project-URL: Documentation, https://github.com/djoezeke/uinex#readme
Project-URL: Homepage, https://github.com/djoezeke/uinex
Project-URL: Issues, https://github.com/djoezeke/uinex/issues
Project-URL: Release Notes, https://github.com/djoezeke/uinex/releases
Project-URL: Source, https://github.com/djoezeke/uinex
Provides-Extra: dev
Provides-Extra: docs
